[{"identifier":"0","tickCollection":["49","50"]},{"identifier":"1","tickCollection":["56","57","58"]},{"identifier":"2","tickCollection":["71","72"]},{"identifier":"3","tickCollection":["75","76","77"]},{"identifier":"4","tickCollection":["99","100"]},{"identifier":"5","tickCollection":["108","109","110"]},{"identifier":"6","tickCollection":["116","117"]},{"identifier":"7","tickCollection":["120","121","122"]},{"identifier":"8","tickCollection":["124","125","126","127"]},{"identifier":"9","tickCollection":["133","134"]},{"identifier":"10","tickCollection":["136","137","138"]},{"identifier":"11","tickCollection":["141","142","143","144"]},{"identifier":"12","tickCollection":["150","151"]},{"identifier":"13","tickCollection":["154","155","156"]},{"identifier":"14","tickCollection":["158","159","160","161"]},{"identifier":"15","tickCollection":["167","168"]},{"identifier":"16","tickCollection":["170","171","172"]}]